.coveragerc
LICENSE
MANIFEST.in
README.rst
setup.py
Cual_ID.egg-info/PKG-INFO
Cual_ID.egg-info/SOURCES.txt
Cual_ID.egg-info/dependency_links.txt
Cual_ID.egg-info/requires.txt
Cual_ID.egg-info/top_level.txt
cual_id.egg-info/SOURCES.txt
cualid/__init__.py
cualid/fix.py
cualid/label.py
cualid/mint.py
cualid/tests/__init__.py
cualid/tests/test_fix.py
cualid/tests/test_label.py
cualid/tests/test_mint.py
examples/ids.txt
examples/modified-ids.txt
scripts/cual-id